tests/__init__.py
tests/test_cli.py
tests/test_utils.py
tests/test_version.py
tests/test_zarp.py
tests/utils.py
tests/config/__init__.py
tests/config/test_args.py
tests/config/test_init.py
tests/config/test_parser.py
tests/config/test_run_config.py
tests/config/test_sample_tables.py
tests/config/test_samples.py
tests/files/config_invalid.yaml
tests/files/config_valid.yaml
tests/files/em@pt:y
tests/files/empty
tests/files/sample_table.tsv
zarp/__init__.py
zarp/cli.py
zarp/utils.py
zarp/version.py
zarp/zarp.py
zarp/config/__init__.py
zarp/config/args.py
zarp/config/enums.py
zarp/config/init.py
zarp/config/models.py
zarp/config/parser.py
zarp/config/run_config.py
zarp/config/sample_tables.py
zarp/config/samples.py
zarp/extensions/__init__.py
zarp/extensions/ensembl.py
zarp/extensions/htsinfer.py
zarp/extensions/sra.py
zarp/run/__init__.py
zarp/run/cleanup.py
zarp/run/snakemake.py
zarp-0.1.1.dist-info/LICENSE
zarp-0.1.1.dist-info/METADATA
zarp-0.1.1.dist-info/WHEEL
zarp-0.1.1.dist-info/entry_points.txt
zarp-0.1.1.dist-info/top_level.txt
zarp-0.1.1.dist-info/RECORD
