Metadata-Version: 2.1
Name: zarp
Version: 0.1.1
Summary: User-friendly command-line interface for the ZARP RNA-Seq analysis pipeline
Home-page: https://git.scicore.unibas.ch/zavolan_group/tools/zarp-cli
Author: Zavolan Lab
Author-email: zavolab-biozentrum@unibas.ch
Maintainer: Zavolan Lab
Maintainer-email: zavolab-biozentrum@unibas.ch
Project-URL: Repository, https://git.scicore.unibas.ch/zavolan_group/tools/zarp-cli
Project-URL: Tracker, https://git.scicore.unibas.ch/zavolan_group/tools/zarp-cli/-/issues
Keywords: bioinformatics,workflow,ngs,high-throughput sequencing
Classifier: Environment :: Console
Classifier: Intended Audience :: Science/Research
Classifier: License :: OSI Approved :: Apache Software License
Classifier: Natural Language :: English
Classifier: Programming Language :: Python :: 3.6
Classifier: Programming Language :: Python :: 3.7
Classifier: Programming Language :: Python :: 3.8
Classifier: Programming Language :: Python :: 3.9
Classifier: Topic :: Scientific/Engineering :: Bio-Informatics
Classifier: Topic :: Utilities
License-File: LICENSE
Requires-Dist: addict (==2.4.0)
Requires-Dist: bidict (==0.22.0)
Requires-Dist: email-validator (==1.2.1)
Requires-Dist: jsonref (==0.2)
Requires-Dist: pandas (==1.3.5)
Requires-Dist: pydantic (==1.9.2)
Requires-Dist: pydantic-collections (==0.3.0)
Requires-Dist: Pygments (==2.8.0)
Requires-Dist: rich (==12.5.1)
